LICENSE.txt
MANIFEST.in
README.md
requirements.txt
setup.py
unn/__init__.py
unn/cli.py
unn/config.py
unn/unn
unn/unn.py
unn.egg-info/PKG-INFO
unn.egg-info/SOURCES.txt
unn.egg-info/dependency_links.txt
unn.egg-info/requires.txt
unn.egg-info/top_level.txt